tf_tagguard/__init__.py
tf_tagguard/cli.py
tf_tagguard/exceptions.py
tf_tagguard/utils.py
tf_tagguard/validator.py
tf_tagguard-1.0.0.dist-info/licenses/LICENSE
tf_tagguard-1.0.0.dist-info/METADATA
tf_tagguard-1.0.0.dist-info/WHEEL
tf_tagguard-1.0.0.dist-info/entry_points.txt
tf_tagguard-1.0.0.dist-info/top_level.txt
tf_tagguard-1.0.0.dist-info/RECORD
