Metadata-Version: 2.4
Name: tf-tagguard
Version: 1.0.0
Summary: CLI tool to validate and enforce AWS tags for resources deployed using Terraform. Targeted for CI/CD pipelines and CLI environments.
Author-email: Mxyzptlk <noreply@noreply.com>
License: MIT
Project-URL: homepage, https://github.com/name/tf-tagguard
Project-URL: repository, https://github.com/name/tf-tagguard/issues
Keywords: terraform,aws,tags,validation,ci/cd
Classifier: Programming Language :: Python :: 3
Classifier: License :: OSI Approved :: MIT License
Classifier: Operating System :: OS Independent
Requires-Python: >=3.8
License-File: LICENSE
Requires-Dist: tabulate<1.0,>=0.9
Requires-Dist: typer<1.0,>=0.9
Dynamic: license-file
